ganslate/__init__.py
ganslate/configs/__init__.py
ganslate/configs/base.py
ganslate/configs/config.py
ganslate/configs/inference.py
ganslate/configs/training.py
ganslate/configs/utils.py
ganslate/configs/validation_testing.py
ganslate/data/__init__.py
ganslate/data/paired_image_dataset.py
ganslate/data/samplers.py
ganslate/data/unpaired_image_dataset.py
ganslate/data/utils/__init__.py
ganslate/data/utils/body_mask.py
ganslate/data/utils/fov_truncate.py
ganslate/data/utils/image_pool.py
ganslate/data/utils/normalization.py
ganslate/data/utils/ops.py
ganslate/data/utils/registration_methods.py
ganslate/data/utils/stochastic_focal_patching.py
ganslate/data/utils/transforms.py
ganslate/engines/__init__.py
ganslate/engines/base.py
ganslate/engines/inferer.py
ganslate/engines/trainer.py
ganslate/engines/utils.py
ganslate/engines/validator_tester.py
ganslate/nn/__init__.py
ganslate/nn/attention.py
ganslate/nn/invertible.py
ganslate/nn/separable.py
ganslate/nn/utils.py
ganslate/nn/discriminators/__init__.py
ganslate/nn/discriminators/patchgan/__init__.py
ganslate/nn/discriminators/patchgan/multiscale_patchgan3d.py
ganslate/nn/discriminators/patchgan/patchgan2d.py
ganslate/nn/discriminators/patchgan/patchgan3d.py
ganslate/nn/discriminators/patchgan/selfattention_patchgan3d.py
ganslate/nn/gans/__init__.py
ganslate/nn/gans/base.py
ganslate/nn/gans/paired/__init__.py
ganslate/nn/gans/paired/pix2pix.py
ganslate/nn/gans/unpaired/__init__.py
ganslate/nn/gans/unpaired/cut.py
ganslate/nn/gans/unpaired/cyclegan.py
ganslate/nn/gans/unpaired/revgan.py
ganslate/nn/generators/__init__.py
ganslate/nn/generators/resnet/__init__.py
ganslate/nn/generators/resnet/piresnet3d.py
ganslate/nn/generators/resnet/resnet2d.py
ganslate/nn/generators/resnet/resnet3d.py
ganslate/nn/generators/unet/__init__.py
ganslate/nn/generators/unet/unet2d.py
ganslate/nn/generators/unet/unet3d.py
ganslate/nn/generators/vnet/__init__.py
ganslate/nn/generators/vnet/selfattention_vnet3d.py
ganslate-0.1.1.dist-info/LICENSE
ganslate-0.1.1.dist-info/METADATA
ganslate-0.1.1.dist-info/WHEEL
ganslate-0.1.1.dist-info/entry_points.txt
ganslate-0.1.1.dist-info/top_level.txt
ganslate-0.1.1.dist-info/RECORD
