Metadata-Version: 2.1
Name: ganslate
Version: 0.1.1
Summary: GAN image-to-image translation framework made simple and extensible.
Home-page: https://github.com/Maastro-CDS-Imaging-Group/ganslate
Author: "ganslate team"
License: mit
Project-URL: Documentation, https://ganslate.readthedocs.io/en/latest/
Keywords: one,two
Platform: any
Classifier: Development Status :: 3 - Alpha
Classifier: Programming Language :: Python :: 3 :: Only
Classifier: Intended Audience :: Science/Research
License-File: LICENSE
Requires-Dist: torch
Requires-Dist: opencv-python
Requires-Dist: simpleitk
Requires-Dist: memcnn
Requires-Dist: loguru
Requires-Dist: wandb
Requires-Dist: tensorboard
Requires-Dist: monai
Requires-Dist: scipy
Requires-Dist: scikit-image
Requires-Dist: omegaconf
Requires-Dist: pandas
Requires-Dist: click
Requires-Dist: cookiecutter
Requires-Dist: wget
Provides-Extra: testing
Requires-Dist: pytest ; extra == 'testing'
Requires-Dist: pytest-cov ; extra == 'testing'
